Metadata-Version: 2.1
Name: django-octicons-context-processor
Version: 2020.7.1
Summary: Django octicons context processor
Home-page: https://github.com/andrewp-as-is/django-octicons-context-processor.py
License: Unlicense
Keywords: django octicons
Platform: UNKNOWN
Classifier: Framework :: Django
Classifier: License :: Public Domain
Classifier: Operating System :: OS Independent
Classifier: Programming Language :: Python :: 3
